MANIFEST.in
README.md
dialog_engine.py
dialog_tree.json
e-pet.py
game_engine.py
input_handler.py
pet.py
pet_names.txt
requirements.txt
save_manager.py
settings.json
settings_manager.py
setup.cfg
ui_manager.py
validate_dialog.py
e_pet-0.3.1.data/data/dialog_tree.json
e_pet-0.3.1.data/data/pet_names.txt
e_pet-0.3.1.data/data/settings.json
e_pet.egg-info/PKG-INFO
e_pet.egg-info/SOURCES.txt
e_pet.egg-info/dependency_links.txt
e_pet.egg-info/entry_points.txt
e_pet.egg-info/requires.txt
e_pet.egg-info/top_level.txt
tests/__init__.py
tests/test_input.py
tests/test_text_wrap.py
tests/test_ui.py
tests/test_wrapping.py
e_pet-0.3.1.dist-info/METADATA
e_pet-0.3.1.dist-info/WHEEL
e_pet-0.3.1.dist-info/entry_points.txt
e_pet-0.3.1.dist-info/top_level.txt
e_pet-0.3.1.dist-info/RECORD
