Metadata-Version: 2.4
Name: e-pet
Version: 0.3.1
Summary: A virtual pet companion CLI application
Home-page: https://github.com/athuler/e-pet
Author: Andrei Thüler
Author-email: info@andreithuler.com
Project-URL: Bug Reports, https://github.com/athuler/e-pet/issues
Project-URL: Donate, https://ko-fi.com/andreithuler
Project-URL: Source, https://github.com/athuler/e-pet
Keywords: virtual pet,cli,game,simulation,terminal,simulation
Classifier: Development Status :: 4 - Beta
Classifier: Intended Audience :: End Users/Desktop
Classifier: License :: OSI Approved :: MIT License
Classifier: Operating System :: OS Independent
Classifier: Programming Language :: Python :: 3
Classifier: Programming Language :: Python :: 3.7
Classifier: Programming Language :: Python :: 3.8
Classifier: Programming Language :: Python :: 3.9
Classifier: Programming Language :: Python :: 3.10
Classifier: Programming Language :: Python :: 3.11
Classifier: Topic :: Games/Entertainment :: Simulation
Classifier: Environment :: Console
Requires-Python: >=3.7
Requires-Dist: rich>=13.0.0
Requires-Dist: importlib_resources>=5.0.0; python_version < "3.9"
Requires-Dist: importlib_resources>=5.0.0; python_version < "3.9"
Dynamic: author
Dynamic: author-email
Dynamic: classifier
Dynamic: description
Dynamic: description-content-type
Dynamic: home-page
Dynamic: keywords
Dynamic: project-url
Dynamic: requires-dist
Dynamic: requires-python
Dynamic: summary
